jsonsteg/__init__.py
jsonsteg/array_reader.py
jsonsteg/array_writer.py
jsonsteg/dict_reader.py
jsonsteg/dict_writer.py
jsonsteg/utils/__init__.py
jsonsteg/utils/byte_converter.py
jsonsteg-1.0.0.dist-info/LICENSE
jsonsteg-1.0.0.dist-info/METADATA
jsonsteg-1.0.0.dist-info/WHEEL
jsonsteg-1.0.0.dist-info/entry_points.txt
jsonsteg-1.0.0.dist-info/RECORD
