Metadata-Version: 2.1
Name: jsonsteg
Version: 1.0.0
Summary: Write payload into JSON without modifying it
License: MIT
Author: PyryL
Author-email: pyry@pyry.info
Requires-Python: >=3.9,<4.0
Classifier: License :: OSI Approved :: MIT License
Classifier: Programming Language :: Python :: 3
Classifier: Programming Language :: Python :: 3.9
Classifier: Programming Language :: Python :: 3.10
Classifier: Programming Language :: Python :: 3.11
